<annotation>
	<folder>Label2</folder>
	<filename>IMG_1279.jpeg</filename>
	<path>C:\Users\cy\Desktop\Label2\IMG_1279.jpeg</path>
	<source>
		<database>Unknown</database>
	</source>
	<size>
		<width>4032</width>
		<height>3024</height>
		<depth>3</depth>
	</size>
	<segmented>0</segmented>
	<object>
		<name>EISSTERN</name>
		<pose>Unspecified</pose>
		<truncated>0</truncated>
		<difficult>0</difficult>
		<bndbox>
			<xmin>2198</xmin>
			<ymin>1607</ymin>
			<xmax>2670</xmax>
			<ymax>2031</ymax>
		</bndbox>
	</object>
</annotation>
